dogma/__init__.py
dogma/amino_acids.py
dogma/codons.py
dogma/genetic_codes.py
dogma/nbci.py
dogma/nucleotides.py
dogma/oligonucleotides.py
dogma/oligonucleotides_simple.py
dogma/proteins.py
dogma/utils.py
dogma/extensions/__init__.py
dogma/extensions/codon_selection.py
dogma/extensions/degenerate_codon_selection/__init__.py
dogma/extensions/degenerate_codon_selection/codon_option.py
dogma/extensions/degenerate_codon_selection/codon_selector.py
dogma/extensions/nonequimolar_codon_optimization/__init__.py
dogma/extensions/nonequimolar_codon_optimization/config.py
dogma/extensions/nonequimolar_codon_optimization/lite_dogma.py
dogma/extensions/nonequimolar_codon_optimization/optimizer.py
dogma/extensions/nonequimolar_codon_optimization/utils.py
dogma/extensions/spiked_oligonucleotides/__init__.py
dogma/extensions/spiked_oligonucleotides/analysis.py
dogma/extensions/spiked_oligonucleotides/mixed_oligonucleotides.py
dogma/extensions/spiked_oligonucleotides/oligo_mixer.py
dogma/extensions/spiked_oligonucleotides/utils.py
dogma-1.0.2.dist-info/LICENSE
dogma-1.0.2.dist-info/METADATA
dogma-1.0.2.dist-info/WHEEL
dogma-1.0.2.dist-info/entry_points.txt
dogma-1.0.2.dist-info/top_level.txt
dogma-1.0.2.dist-info/RECORD
