Metadata-Version: 2.1
Name: dogma
Version: 1.0.2
Summary: Collection of object-oriented entities related by the central dogma of biology.
Home-page: https://github.com/griffinclausen/dogma
Author: Griffin Clausen
Author-email: dogma.maintainer@gmail.com
License: MIT
Platform: UNKNOWN
Requires-Dist: pandas
